pelix/__init__.py
pelix/constants.py
pelix/framework.py
pelix/ipv6utils.py
pelix/ldapfilter.py
pelix/threadpool.py
pelix/utilities.py
pelix/http/__init__.py
pelix/http/basic.py
pelix/http/routing.py
pelix/internals/__init__.py
pelix/internals/events.py
pelix/internals/hooks.py
pelix/internals/registry.py
pelix/ipopo/__init__.py
pelix/ipopo/constants.py
pelix/ipopo/contexts.py
pelix/ipopo/core.py
pelix/ipopo/decorators.py
pelix/ipopo/instance.py
pelix/ipopo/waiting.py
pelix/ipopo/handlers/__init__.py
pelix/ipopo/handlers/constants.py
pelix/ipopo/handlers/properties.py
pelix/ipopo/handlers/provides.py
pelix/ipopo/handlers/requires.py
pelix/ipopo/handlers/requiresbest.py
pelix/ipopo/handlers/requiresbroadcast.py
pelix/ipopo/handlers/requiresmap.py
pelix/ipopo/handlers/requiresvarfilter.py
pelix/ipopo/handlers/temporal.py
pelix/misc/__init__.py
pelix/misc/eventadmin_printer.py
pelix/misc/init_handler.py
pelix/misc/jabsorb.py
pelix/misc/log.py
pelix/misc/mqtt_client.py
pelix/misc/ssl_wrap.py
pelix/misc/xmpp.py
pelix/remote/__init__.py
pelix/remote/beans.py
pelix/remote/dispatcher.py
pelix/remote/edef_io.py
pelix/remote/json_rpc.py
pelix/remote/registry.py
pelix/remote/xml_rpc.py
pelix/remote/discovery/__init__.py
pelix/remote/discovery/mdns.py
pelix/remote/discovery/mqtt.py
pelix/remote/discovery/multicast.py
pelix/remote/discovery/redis.py
pelix/remote/discovery/zookeeper.py
pelix/remote/transport/__init__.py
pelix/remote/transport/commons.py
pelix/remote/transport/jabsorb_rpc.py
pelix/remote/transport/mqtt_rpc.py
pelix/rsa/__init__.py
pelix/rsa/edef.py
pelix/rsa/endpointdescription.py
pelix/rsa/remoteserviceadmin.py
pelix/rsa/shell.py
pelix/rsa/providers/__init__.py
pelix/rsa/providers/discovery/__init__.py
pelix/rsa/providers/discovery/discovery_etcd.py
pelix/rsa/providers/discovery/etcd3/__init__.py
pelix/rsa/providers/discovery/etcd3/etcdrpc/__init__.py
pelix/rsa/providers/discovery/etcd3/etcdrpc/auth.proto
pelix/rsa/providers/discovery/etcd3/etcdrpc/auth_pb2.py
ipopo-3.1.0.dist-info/METADATA
ipopo-3.1.0.dist-info/WHEEL
ipopo-3.1.0.dist-info/licenses/LICENSE
ipopo-3.1.0.dist-info/RECORD
