Metadata-Version: 2.4
Name: iPOPO
Version: 3.1.0
Summary: A service-oriented component model framework
Project-URL: Homepage, https://ipopo.readthedocs.io/
Project-URL: Documentation, https://ipopo.readthedocs.io/
Project-URL: Issues, http://github.com/tcalmant/ipopo/issues
Project-URL: Source, http://github.com/tcalmant/ipopo/
Author-email: Thomas Calmant <thomas.calmant+github@gmail.com>
License-Expression: Apache-2.0
License-File: LICENSE
Classifier: Development Status :: 5 - Production/Stable
Classifier: Environment :: Console
Classifier: Intended Audience :: Developers
Classifier: License :: OSI Approved :: Apache Software License
Classifier: Operating System :: OS Independent
Classifier: Programming Language :: Python :: 3.10
Classifier: Programming Language :: Python :: 3.11
Classifier: Programming Language :: Python :: 3.12
Classifier: Programming Language :: Python :: 3.13
Classifier: Topic :: Software Development :: Libraries :: Application Frameworks
Requires-Python: >=3.10
Requires-Dist: jsonrpclib-pelix>=0.4.3
Provides-Extra: etcd2
Requires-Dist: osgiservicebridge>=1.5.8; extra == 'etcd2'
Requires-Dist: python-etcd==0.4.5; extra == 'etcd2'
Provides-Extra: mqtt
Requires-Dist: paho-mqtt>=2.1; extra == 'mqtt'
Provides-Extra: redis
Requires-Dist: redis>=2.10; extra == 'redis'
Provides-Extra: rsa
Requires-Dist: grpcio-tools>=1.71.0; extra == 'rsa'
Requires-Dist: grpcio>=1.71.0; extra == 'rsa'
Requires-Dist: osgiservicebridge>=1.5.8; extra == 'rsa'
Provides-Extra: xmpp
Requires-Dist: slixmpp==1.10; extra == 'xmpp'
Provides-Extra: yaml
Requires-Dist: pyyaml>=6.0; extra == 'yaml'
Provides-Extra: zeroconf
Requires-Dist: zeroconf==0.19; extra == 'zeroconf'
Provides-Extra: zookeeper
Requires-Dist: kazoo==2.8.0; extra == 'zookeeper'
